ampltools/__init__.py
ampltools/notebooks.py
ampltools/utils.py
ampltools/.vscode/settings.json
ampltools/bundle/__init__.py
ampltools/bundle/__main__.py
ampltools/bundle/bundle.py
ampltools/modules/__init__.py
ampltools/modules/__main__.py
ampltools/modules/amplpypi.py
ampltools/modules/commands.py
ampltools/modules/utils.py
ampltools/tests/TestBase.py
ampltools/tests/__init__.py
ampltools/tests/__main__.py
ampltools/tests/test_install.py
ampltools/tests/test_load.py
ampltools/tests/test_preload.py
ampltools/tests/test_run.py
ampltools-0.7.4.dist-info/LICENSE
ampltools-0.7.4.dist-info/METADATA
ampltools-0.7.4.dist-info/WHEEL
ampltools-0.7.4.dist-info/top_level.txt
ampltools-0.7.4.dist-info/RECORD
