Metadata-Version: 2.1
Name: ampltools
Version: 0.7.4
Summary: AMPL Python Tools
Home-page: http://ampl.com/
Download-URL: https://github.com/ampl/amplpy/tree/master/ampltools
Author: Filipe Brandão
Author-email: fdabrandao@ampl.com
License: BSD-3
Platform: any
Classifier: Development Status :: 4 - Beta
Classifier: Environment :: Console
Classifier: Topic :: Software Development
Classifier: Topic :: Scientific/Engineering
Classifier: Intended Audience :: Developers
Classifier: Intended Audience :: Science/Research
Classifier: License :: OSI Approved :: BSD License
Classifier: Operating System :: POSIX
Classifier: Operating System :: Unix
Classifier: Operating System :: MacOS
Classifier: Operating System :: Microsoft :: Windows
Classifier: Programming Language :: Python
Classifier: Programming Language :: Python :: 3
Classifier: Programming Language :: Python :: Implementation :: CPython
License-File: LICENSE
